{
 "nodes": [
  {
   "id": 1215072,
   "group": 2,
   "name": "Clea Lewis"
  },
  {
   "id": 164397,
   "group": 2,
   "name": "Callie Thorne"
  },
  {
   "id": 1090276,
   "group": 2,
   "name": "Alison Becker"
  },
  {
   "id": 11825,
   "group": 2,
   "name": "Maggie Grace"
  },
  {
   "id": 70767,
   "group": 2,
   "name": "Drea de Matteo"
  },
  {
   "id": 122888,
   "group": 2,
   "name": "Ashley Williams"
  },
  {
   "id": 81953,
   "group": 2,
   "name": "Katie Walder"
  },
  {
   "id": 163906,
   "group": 2,
   "name": "Erin Dilly"
  },
  {
   "id": 16502,
   "group": 2,
   "name": "Geraldine Hughes"
  },
  {
   "id": 935,
   "group": 2,
   "name": "Connie Nielsen"
  },
  {
   "id": 82885,
   "group": 2,
   "name": "Zoe Lister-Jones"
  },
  {
   "id": 17495,
   "group": 2,
   "name": "Martha Plimpton"
  },
  {
   "id": 74932,
   "group": 2,
   "name": "Paige Turco"
  },
  {
   "id": 91461,
   "group": 2,
   "name": "Michelle Hurd"
  },
  {
   "id": 133047,
   "group": 2,
   "name": "Betsy Aidem"
  },
  {
   "id": 59696,
   "group": 2,
   "name": "Trieste Kelly Dunn"
  },
  {
   "id": 1100549,
   "group": 2,
   "name": "Marina Squerciati"
  },
  {
   "id": 1223878,
   "group": 2,
   "name": "Emily Kinney"
  },
  {
   "id": 118043,
   "group": 2,
   "name": "Francie Swift"
  },
  {
   "id": 1232555,
   "group": 2,
   "name": "Marlyne Barrett"
  },
  {
   "id": 126713,
   "group": 2,
   "name": "Elizabeth Marvel"
  },
  {
   "id": 21129,
   "group": 2,
   "name": "Marla Sucharetza"
  },
  {
   "id": 4888,
   "group": 2,
   "name": "Lily Rabe"
  },
  {
   "id": 22127,
   "group": 2,
   "name": "Christina Kirk"
  },
  {
   "id": 1218184,
   "group": 2,
   "name": "Hettienne Park"
  },
  {
   "id": 1218223,
   "group": 2,
   "name": "Kat Foster"
  },
  {
   "id": 87932,
   "group": 2,
   "name": "Ren\u00e9e Elise Goldsberry"
  },
  {
   "id": 129104,
   "group": 2,
   "name": "Melissa Benoist"
  },
  {
   "id": 14984,
   "group": 2,
   "name": "Jessica Hecht"
  },
  {
   "id": 80622,
   "group": 2,
   "name": "Suzzanne Douglas"
  },
  {
   "id": 154698,
   "group": 2,
   "name": "Caprice Benedetti"
  },
  {
   "id": 23627,
   "group": 2,
   "name": "Patricia Kalember"
  },
  {
   "id": 1170657,
   "group": 2,
   "name": "Amanda Warren"
  },
  {
   "id": 163695,
   "group": 2,
   "name": "Leslie Hendrix"
  },
  {
   "id": 155574,
   "group": 2,
   "name": "Enid Graham"
  },
  {
   "id": 110316,
   "group": 2,
   "name": "Judy Kuhn"
  },
  {
   "id": 130513,
   "group": 2,
   "name": "Geneva Carr"
  },
  {
   "id": 59206,
   "group": 2,
   "name": "Becky Ann Baker"
  },
  {
   "id": 43366,
   "group": 2,
   "name": "Ann Dowd"
  },
  {
   "id": 20047,
   "group": 2,
   "name": "Cara Buono"
  },
  {
   "id": 58168,
   "group": 2,
   "name": "Rachelle Lefevre"
  },
  {
   "id": 1222175,
   "group": 2,
   "name": "Becki Newton"
  },
  {
   "id": 109869,
   "group": 2,
   "name": "Kristen Schaal"
  },
  {
   "id": 78434,
   "group": 2,
   "name": "America Olivo"
  },
  {
   "id": 63735,
   "group": 2,
   "name": "Misti Traya"
  },
  {
   "id": 15423,
   "group": 2,
   "name": "Paget Brewster"
  },
  {
   "id": 33488,
   "group": 2,
   "name": "Helen Slater"
  },
  {
   "id": 42335,
   "group": 2,
   "name": "Kathleen Wilhoite"
  },
  {
   "id": 3664,
   "group": 2,
   "name": "Sandra Bernhard"
  },
  {
   "id": 155698,
   "group": 2,
   "name": "Jackie Debatin"
  },
  {
   "id": 65797,
   "group": 2,
   "name": "Catherine Dent"
  },
  {
   "id": 1102,
   "group": 2,
   "name": "Elpidia Carrillo"
  },
  {
   "id": 173198,
   "group": 2,
   "name": "Heather Tom"
  },
  {
   "id": 166566,
   "group": 2,
   "name": "Marguerite MacIntyre"
  },
  {
   "id": 134082,
   "group": 2,
   "name": "Amy Pietz"
  },
  {
   "id": 85143,
   "group": 2,
   "name": "Angela Sarafyan"
  },
  {
   "id": 60632,
   "group": 2,
   "name": "Rebecca Wisocky"
  },
  {
   "id": 134365,
   "group": 2,
   "name": "Fernanda Andrade"
  },
  {
   "id": 175660,
   "group": 2,
   "name": "Zoe McLellan"
  },
  {
   "id": 159325,
   "group": 2,
   "name": "Melissa Marsala"
  },
  {
   "id": 110463,
   "group": 2,
   "name": "Lauren Stamile"
  },
  {
   "id": 77803,
   "group": 2,
   "name": "Keri Lynn Pratt"
  },
  {
   "id": 1242775,
   "group": 2,
   "name": "Amelia Rose Blaire"
  },
  {
   "id": 121566,
   "group": 2,
   "name": "Sharon Lawrence"
  },
  {
   "id": 105646,
   "group": 2,
   "name": "Linda Park"
  },
  {
   "id": 212154,
   "group": 2,
   "name": "Deborah Ann Woll"
  },
  {
   "id": 65345,
   "group": 2,
   "name": "Sandrine Holt"
  },
  {
   "id": 1213613,
   "group": 2,
   "name": "Jeri Ryan"
  },
  {
   "id": 11024,
   "group": 2,
   "name": "Kelly Hu"
  },
  {
   "id": 21124,
   "group": 2,
   "name": "Paula Garc\u00e9s"
  },
  {
   "id": 30485,
   "group": 2,
   "name": "CCH Pounder"
  },
  {
   "id": 49425,
   "group": 2,
   "name": "Annabeth Gish"
  },
  {
   "id": 143235,
   "group": 2,
   "name": "Vanessa Aspillaga"
  },
  {
   "id": 1387448,
   "group": 2,
   "name": "Amber Skye Noyes"
  },
  {
   "id": 171733,
   "group": 2,
   "name": "Francesca Faridany"
  },
  {
   "id": 59261,
   "group": 2,
   "name": "Hannah Marks"
  },
  {
   "id": 118243,
   "group": 2,
   "name": "Sprague Grayden"
  },
  {
   "id": 31171,
   "group": 2,
   "name": "Julie Bowen"
  },
  {
   "id": 31649,
   "group": 2,
   "name": "Brooke Smith"
  },
  {
   "id": 73836,
   "group": 2,
   "name": "Laura Regan"
  },
  {
   "id": 52776,
   "group": 2,
   "name": "Dagmara Domi\u0144czyk"
  },
  {
   "id": 74537,
   "group": 2,
   "name": "Maggie Siff"
  },
  {
   "id": 58692,
   "group": 2,
   "name": "Melinda McGraw"
  },
  {
   "id": 198927,
   "group": 2,
   "name": "Sarah Drew"
  },
  {
   "id": 14892,
   "group": 2,
   "name": "Rosemarie DeWitt"
  },
  {
   "id": 78805,
   "group": 2,
   "name": "Laura Leighton"
  },
  {
   "id": 25869,
   "group": 2,
   "name": "Reiko Aylesworth"
  },
  {
   "id": 101028,
   "group": 2,
   "name": "Michelle Borth"
  },
  {
   "id": 1039525,
   "group": 2,
   "name": "Lili Simmons"
  },
  {
   "id": 56825,
   "group": 2,
   "name": "Sarah Carter"
  },
  {
   "id": 170880,
   "group": 2,
   "name": "Jennifer Hall"
  },
  {
   "id": 20767,
   "group": 2,
   "name": "Samantha Mathis"
  },
  {
   "id": 18261,
   "group": 2,
   "name": "Jayne Atkinson"
  },
  {
   "id": 92327,
   "group": 2,
   "name": "Lindsay Hollister"
  },
  {
   "id": 2453,
   "group": 2,
   "name": "Mary Steenburgen"
  },
  {
   "id": 5958,
   "group": 2,
   "name": "Hilary Duff"
  },
  {
   "id": 96554,
   "group": 2,
   "name": "Mary Mara"
  },
  {
   "id": 109740,
   "group": 2,
   "name": "Alysia Reiner"
  },
  {
   "id": 52929,
   "group": 2,
   "name": "Angie Harmon"
  },
  {
   "id": 78501,
   "group": 2,
   "name": "Melissa Joan Hart"
  },
  {
   "id": 62220,
   "group": 2,
   "name": "Lauren Cohan"
  },
  {
   "id": 177443,
   "group": 2,
   "name": "Tracy Pollan"
  },
  {
   "id": 14415,
   "group": 2,
   "name": "Julie Hagerty"
  },
  {
   "id": 171075,
   "group": 2,
   "name": "Chandra Wilson"
  },
  {
   "id": 171673,
   "group": 2,
   "name": "Kathleen McNenny"
  },
  {
   "id": 10399,
   "group": 2,
   "name": "Teri Polo"
  },
  {
   "id": 1308445,
   "group": 2,
   "name": "Carrie Coon"
  },
  {
   "id": 58966,
   "group": 2,
   "name": "Deirdre Lovejoy"
  },
  {
   "id": 84422,
   "group": 2,
   "name": "Carolyn McCormick"
  },
  {
   "id": 27260,
   "group": 2,
   "name": "Laila Robins"
  },
  {
   "id": 167604,
   "group": 2,
   "name": "Nadia Dajani"
  },
  {
   "id": 1218027,
   "group": 2,
   "name": "Anna Holbrook"
  },
  {
   "id": 1218146,
   "group": 2,
   "name": "Tricia Paoluccio"
  },
  {
   "id": 1218158,
   "group": 2,
   "name": "Adrianne Frost"
  },
  {
   "id": 65002,
   "group": 2,
   "name": "Dana Delany"
  },
  {
   "id": 1318650,
   "group": 2,
   "name": "Willa Fitzgerald"
  },
  {
   "id": 73569,
   "group": 2,
   "name": "Dana Eskelson"
  },
  {
   "id": 58369,
   "group": 2,
   "name": "Alexandra Breckenridge"
  },
  {
   "id": 970769,
   "group": 2,
   "name": "Rachel Hilson"
  },
  {
   "id": 14702,
   "group": 2,
   "name": "Cathy Moriarty"
  },
  {
   "id": 25933,
   "group": 2,
   "name": "Emily Deschanel"
  },
  {
   "id": 18285,
   "group": 2,
   "name": "Jennifer Esposito"
  },
  {
   "id": 4721,
   "group": 2,
   "name": "Jill Scott"
  },
  {
   "id": 964397,
   "group": 2,
   "name": "Miranda Lambert"
  },
  {
   "id": 23959,
   "group": 2,
   "name": "Debra Messing"
  },
  {
   "id": 171649,
   "group": 2,
   "name": "Rebecca Creskoff"
  },
  {
   "id": 1232582,
   "group": 2,
   "name": "Rebecca Luker"
  },
  {
   "id": 21702,
   "group": 2,
   "name": "Ming-Na Wen"
  },
  {
   "id": 10739,
   "group": 2,
   "name": "Bebe Neuwirth"
  },
  {
   "id": 84877,
   "group": 2,
   "name": "Robin Paul"
  },
  {
   "id": 11617,
   "group": 2,
   "name": "Mischa Barton"
  },
  {
   "id": 21216,
   "group": 2,
   "name": "Kim Delaney"
  },
  {
   "id": 27563,
   "group": 2,
   "name": "Amy Irving"
  },
  {
   "id": 20189,
   "group": 2,
   "name": "Amy Smart"
  },
  {
   "id": 4687,
   "group": 2,
   "name": "Patricia Arquette"
  },
  {
   "id": 187565,
   "group": 2,
   "name": "Audra McDonald"
  },
  {
   "id": 18282,
   "group": 2,
   "name": "Karina Arroyave"
  },
  {
   "id": 16181,
   "group": 2,
   "name": "Haviland Morris"
  },
  {
   "id": 134178,
   "group": 2,
   "name": "Patricia Richardson"
  },
  {
   "id": 28412,
   "group": 2,
   "name": "Rebecca De Mornay"
  },
  {
   "id": 25836,
   "group": 2,
   "name": "Sarah Clarke"
  },
  {
   "id": 33689,
   "group": 2,
   "name": "Charlayne Woodard"
  },
  {
   "id": 4726,
   "group": 2,
   "name": "Marcia Gay Harden"
  },
  {
   "id": 70776,
   "group": 2,
   "name": "Kellee Stewart"
  },
  {
   "id": 65639,
   "group": 2,
   "name": "Diane Neal"
  },
  {
   "id": 164040,
   "group": 2,
   "name": "Wendy Hoopes"
  },
  {
   "id": 1221134,
   "group": 2,
   "name": "Jennifer Ferrin"
  },
  {
   "id": 17640,
   "group": 2,
   "name": "Susan Misner"
  },
  {
   "id": 92728,
   "group": 2,
   "name": "Amy Hargreaves"
  },
  {
   "id": 151363,
   "group": 2,
   "name": "Kate Hodge"
  },
  {
   "id": 20387,
   "group": 2,
   "name": "Clea DuVall"
  },
  {
   "id": 21321,
   "group": 2,
   "name": "Kristina Klebe"
  },
  {
   "id": 39977,
   "group": 2,
   "name": "Michael Michele"
  },
  {
   "id": 16215,
   "group": 2,
   "name": "Karen Young"
  },
  {
   "id": 11705,
   "group": 2,
   "name": "Michelle Monaghan"
  },
  {
   "id": 13241,
   "group": 2,
   "name": "Estella Warren"
  },
  {
   "id": 6751,
   "group": 2,
   "name": "Siobhan Fallon Hogan"
  },
  {
   "id": 1063,
   "group": 2,
   "name": "Lea Thompson"
  },
  {
   "id": 155669,
   "group": 2,
   "name": "Keesha Sharp"
  },
  {
   "id": 163928,
   "group": 2,
   "name": "Noelle Beck"
  },
  {
   "id": 8985,
   "group": 2,
   "name": "Margaret Colin"
  },
  {
   "id": 50346,
   "group": 2,
   "name": "Shiri Appleby"
  },
  {
   "id": 58643,
   "group": 2,
   "name": "Linda Emond"
  },
  {
   "id": 60034,
   "group": 2,
   "name": "Laura Benanti"
  },
  {
   "id": 44059,
   "group": 2,
   "name": "Jodi Long"
  },
  {
   "id": 216676,
   "group": 2,
   "name": "Sutton Foster"
  },
  {
   "id": 1232500,
   "group": 2,
   "name": "Jayne Houdyshell"
  },
  {
   "id": 21044,
   "group": 2,
   "name": "Lynn Collins"
  },
  {
   "id": 177022,
   "group": 2,
   "name": "Rosalyn Coleman"
  },
  {
   "id": 5578,
   "group": 2,
   "name": "Debi Mazar"
  },
  {
   "id": 161847,
   "group": 2,
   "name": "Gretchen Egolf"
  },
  {
   "id": 88755,
   "group": 2,
   "name": "Jennifer Van Dyck"
  },
  {
   "id": 64908,
   "group": 2,
   "name": "LisaGay Hamilton"
  },
  {
   "id": 1154564,
   "group": 2,
   "name": "Jennifer Lim"
  },
  {
   "id": 1236987,
   "group": 2,
   "name": "Kerry Butler"
  },
  {
   "id": 93663,
   "group": 2,
   "name": "Kellie Martin"
  },
  {
   "id": 156342,
   "group": 2,
   "name": "Romy Rosemont"
  },
  {
   "id": 120831,
   "group": 2,
   "name": "Annaleigh Ashford"
  },
  {
   "id": 171901,
   "group": 2,
   "name": "Lena Georgas"
  },
  {
   "id": 1141113,
   "group": 2,
   "name": "Christiane Noll"
  },
  {
   "id": 27855,
   "group": 2,
   "name": "Shannyn Sossamon"
  },
  {
   "id": 11671,
   "group": 2,
   "name": "Bijou Phillips"
  },
  {
   "id": 149665,
   "group": 2,
   "name": "Kali Rocha"
  },
  {
   "id": 4441,
   "group": 2,
   "name": "Pell James"
  },
  {
   "id": 1279279,
   "group": 2,
   "name": "Virginia Gardner"
  },
  {
   "id": 133451,
   "group": 2,
   "name": "Aya Cash"
  },
  {
   "id": 2525,
   "group": 2,
   "name": "Shannon Cochran"
  },
  {
   "id": 55546,
   "group": 2,
   "name": "Liza Weil"
  },
  {
   "id": 6681,
   "group": 2,
   "name": "Sherilyn Fenn"
  },
  {
   "id": 118546,
   "group": 2,
   "name": "Adina Porter"
  },
  {
   "id": 40060,
   "group": 2,
   "name": "Tina Holmes"
  },
  {
   "id": 65421,
   "group": 2,
   "name": "Elizabeth Rodriguez"
  },
  {
   "id": 115240,
   "group": 2,
   "name": "Lindsay Pulsipher"
  },
  {
   "id": 168610,
   "group": 2,
   "name": "Kathleen Munroe"
  },
  {
   "id": 176823,
   "group": 2,
   "name": "Spencer Grammer"
  },
  {
   "id": 100867,
   "group": 2,
   "name": "Marika Dominczyk"
  },
  {
   "id": 79792,
   "group": 2,
   "name": "Laura Allen"
  },
  {
   "id": 65760,
   "group": 2,
   "name": "Marin Hinkle"
  },
  {
   "id": 17187,
   "group": 2,
   "name": "Trini Alvarado"
  },
  {
   "id": 44830,
   "group": 2,
   "name": "Deborah Rush"
  },
  {
   "id": 1217942,
   "group": 2,
   "name": "Anna Belknap"
  },
  {
   "id": 1218005,
   "group": 2,
   "name": "Mia Dillon"
  },
  {
   "id": 1218132,
   "group": 2,
   "name": "Natascia Diaz"
  },
  {
   "id": 49,
   "group": 2,
   "name": "Maria Bello"
  },
  {
   "id": 1222277,
   "group": 2,
   "name": "Camilla Scott"
  },
  {
   "id": 84457,
   "group": 2,
   "name": "Marisol Nichols"
  },
  {
   "id": 13636,
   "group": 2,
   "name": "Jane Krakowski"
  },
  {
   "id": 19492,
   "group": 2,
   "name": "Viola Davis"
  },
  {
   "id": 129904,
   "group": 2,
   "name": "Kate Levering"
  },
  {
   "id": 73336,
   "group": 2,
   "name": "Summer Bishil"
  },
  {
   "id": 88598,
   "group": 2,
   "name": "Lourdes Benedicto"
  },
  {
   "id": 9281,
   "group": 2,
   "name": "Elizabeth Banks"
  },
  {
   "id": 21711,
   "group": 2,
   "name": "Erika Christensen"
  },
  {
   "id": 31140,
   "group": 2,
   "name": "Mary Stuart Masterson"
  },
  {
   "id": 7796,
   "group": 2,
   "name": "Illeana Douglas"
  },
  {
   "id": 26009,
   "group": 2,
   "name": "Gail O'Grady"
  },
  {
   "id": 1216169,
   "group": 2,
   "name": "Sophina Brown"
  },
  {
   "id": 37252,
   "group": 2,
   "name": "Yvonne Zima"
  },
  {
   "id": 133401,
   "group": 2,
   "name": "Amanda Fuller"
  },
  {
   "id": 19797,
   "group": 2,
   "name": "Marlee Matlin"
  },
  {
   "id": 206637,
   "group": 2,
   "name": "Kelli Giddish"
  },
  {
   "id": 172099,
   "group": 2,
   "name": "Marjan Neshat"
  },
  {
   "id": 41555,
   "group": 2,
   "name": "Melissa Sagemiller"
  },
  {
   "id": 164149,
   "group": 2,
   "name": "Samantha Buck"
  },
  {
   "id": 164343,
   "group": 2,
   "name": "Kristin Griffith"
  },
  {
   "id": 34200,
   "group": 2,
   "name": "Sakina Jaffrey"
  },
  {
   "id": 42694,
   "group": 2,
   "name": "Tamara Tunie"
  },
  {
   "id": 52002,
   "group": 2,
   "name": "Florencia Lozano"
  },
  {
   "id": 78578,
   "group": 2,
   "name": "Angela Oh"
  },
  {
   "id": 54124,
   "group": 2,
   "name": "Marceline Hugot"
  },
  {
   "id": 210826,
   "group": 2,
   "name": "Andrea Navedo"
  },
  {
   "id": 79997,
   "group": 2,
   "name": "Tijuana Ricks"
  },
  {
   "id": 81321,
   "group": 2,
   "name": "Amy Carlson"
  },
  {
   "id": 34612,
   "group": 2,
   "name": "Anna Chlumsky"
  },
  {
   "id": 142293,
   "group": 2,
   "name": "Marisa Ryan"
  },
  {
   "id": 1226076,
   "group": 2,
   "name": "Sherri Saum"
  },
  {
   "id": 38024,
   "group": 2,
   "name": "Cynthia Nixon"
  },
  {
   "id": 107033,
   "group": 2,
   "name": "Anastasia Griffith"
  },
  {
   "id": 78788,
   "group": 2,
   "name": "Lecy Goranson"
  },
  {
   "id": 1213610,
   "group": 2,
   "name": "Karen Goberman"
  },
  {
   "id": 75528,
   "group": 2,
   "name": "Kaitlin Hopkins"
  },
  {
   "id": 24305,
   "group": 2,
   "name": "Julie White"
  },
  {
   "id": 80988,
   "group": 2,
   "name": "Amy Redford"
  },
  {
   "id": 167120,
   "group": 2,
   "name": "Jennifer Dundas"
  },
  {
   "id": 208659,
   "group": 2,
   "name": "Madison McKinley"
  },
  {
   "id": 59156,
   "group": 2,
   "name": "Stephanie March"
  },
  {
   "id": 16859,
   "group": 2,
   "name": "Tammy Blanchard"
  },
  {
   "id": 21369,
   "group": 2,
   "name": "Gloria Reuben"
  },
  {
   "id": 99,
   "group": 2,
   "name": "Amanda Plummer"
  },
  {
   "id": 99351,
   "group": 2,
   "name": "Valerie Mahaffey"
  },
  {
   "id": 51544,
   "group": 2,
   "name": "Mare Winningham"
  },
  {
   "id": 56689,
   "group": 2,
   "name": "LaChanze"
  },
  {
   "id": 4513,
   "group": 2,
   "name": "Elizabeth McGovern"
  },
  {
   "id": 82663,
   "group": 2,
   "name": "Shannon Woodward"
  },
  {
   "id": 53260,
   "group": 2,
   "name": "Adriane Lenox"
  },
  {
   "id": 59257,
   "group": 2,
   "name": "Maria Thayer"
  },
  {
   "id": 33655,
   "group": 2,
   "name": "Erika Alexander"
  },
  {
   "id": 1232610,
   "group": 2,
   "name": "Theo Kogan"
  },
  {
   "id": 1034453,
   "group": 2,
   "name": "La La Anthony"
  },
  {
   "id": 28024,
   "group": 2,
   "name": "Judy Gold"
  },
  {
   "id": 39730,
   "group": 2,
   "name": "Susan Floyd"
  },
  {
   "id": 1030995,
   "group": 2,
   "name": "Jessica Camacho"
  },
  {
   "id": 1465043,
   "group": 2,
   "name": "Ciara Ren\u00e9e"
  },
  {
   "id": 8691,
   "group": 2,
   "name": "Zoe Saldana"
  },
  {
   "id": 15250,
   "group": 2,
   "name": "Hope Davis"
  },
  {
   "id": 1157294,
   "group": 2,
   "name": "Colby Minifie"
  },
  {
   "id": 204468,
   "group": 2,
   "name": "Fiona Dourif"
  },
  {
   "id": 74612,
   "group": 2,
   "name": "Malinda Williams"
  },
  {
   "id": 122231,
   "group": 2,
   "name": "Katherine Moennig"
  },
  {
   "id": 74687,
   "group": 2,
   "name": "Stella Maeve"
  },
  {
   "id": 139150,
   "group": 2,
   "name": "Amy Seimetz"
  },
  {
   "id": 109024,
   "group": 2,
   "name": "Purva Bedi"
  },
  {
   "id": 141610,
   "group": 2,
   "name": "Lauren V\u00e9lez"
  },
  {
   "id": 49824,
   "group": 2,
   "name": "Kathryn Erbe"
  },
  {
   "id": 999346,
   "group": 2,
   "name": "Kylie Bunbury"
  },
  {
   "id": 84247,
   "group": 2,
   "name": "Emily VanCamp"
  },
  {
   "id": 110742,
   "group": 2,
   "name": "Tika Sumpter"
  },
  {
   "id": 15007,
   "group": 2,
   "name": "Laura Harring"
  },
  {
   "id": 154769,
   "group": 2,
   "name": "Allison Munn"
  },
  {
   "id": 16845,
   "group": 2,
   "name": "Nicole Sullivan"
  },
  {
   "id": 100395,
   "group": 2,
   "name": "Josie Bissett"
  },
  {
   "id": 83701,
   "group": 2,
   "name": "Alex Kingston"
  },
  {
   "id": 540281,
   "group": 2,
   "name": "Wendy Williams"
  },
  {
   "id": 59687,
   "group": 2,
   "name": "Starla Benford"
  },
  {
   "id": 15441,
   "group": 2,
   "name": "Mili Avital"
  },
  {
   "id": 1345418,
   "group": 2,
   "name": "Lola Kirke"
  },
  {
   "id": 145814,
   "group": 2,
   "name": "Gage Golightly"
  },
  {
   "id": 3282,
   "group": 2,
   "name": "Sara Gilbert"
  },
  {
   "id": 19265,
   "group": 2,
   "name": "Khandi Alexander"
  },
  {
   "id": 1106256,
   "group": 2,
   "name": "Angelica Page"
  },
  {
   "id": 47882,
   "group": 2,
   "name": "Cynthia Gibb"
  },
  {
   "id": 81678,
   "group": 2,
   "name": "Pooja Kumar"
  },
  {
   "id": 84462,
   "group": 2,
   "name": "Lynn Chen"
  },
  {
   "id": 70852,
   "group": 2,
   "name": "Schuyler Fisk"
  },
  {
   "id": 163115,
   "group": 2,
   "name": "Maureen Flannigan"
  },
  {
   "id": 61830,
   "group": 2,
   "name": "Sylva Kelegian"
  },
  {
   "id": 86468,
   "group": 2,
   "name": "Sarah Wayne Callies"
  },
  {
   "id": 31167,
   "group": 2,
   "name": "Elizabeth Mitchell"
  },
  {
   "id": 39388,
   "group": 2,
   "name": "Amy Ryan"
  },
  {
   "id": 1232324,
   "group": 2,
   "name": "Pippa Black"
  },
  {
   "id": 171379,
   "group": 2,
   "name": "Katherine Borowitz"
  },
  {
   "id": 1443708,
   "group": 2,
   "name": "Kimiko Glenn"
  },
  {
   "id": 62547,
   "group": 2,
   "name": "Susanna Thompson"
  },
  {
   "id": 52996,
   "group": 2,
   "name": "Heather Goldenhersh"
  },
  {
   "id": 94954,
   "group": 2,
   "name": "Katie Chonacas"
  },
  {
   "id": 2138774,
   "group": 2,
   "name": "Rachel Bay Jones"
  },
  {
   "id": 62127,
   "group": 2,
   "name": "Lonette McKee"
  },
  {
   "id": 64826,
   "group": 2,
   "name": "Isabel Glasser"
  },
  {
   "id": 118247,
   "group": 2,
   "name": "Lizette Carri\u00f3n"
  },
  {
   "id": 15109,
   "group": 2,
   "name": "Lisa Roberts Gillan"
  },
  {
   "id": 1213305,
   "group": 2,
   "name": "Star Jones"
  },
  {
   "id": 14668,
   "group": 2,
   "name": "Daphne Zuniga"
  },
  {
   "id": 56441,
   "group": 2,
   "name": "Sheila Tousey"
  },
  {
   "id": 95039,
   "group": 2,
   "name": "Sofia Vassilieva"
  },
  {
   "id": 59962,
   "group": 2,
   "name": "Glynnis O'Connor"
  },
  {
   "id": 9782,
   "group": 2,
   "name": "Tyra Ferrell"
  },
  {
   "id": 12932,
   "group": 2,
   "name": "Barbara Garrick"
  },
  {
   "id": 1074628,
   "group": 2,
   "name": "Elyse Mirto"
  },
  {
   "id": 220620,
   "group": 2,
   "name": "Alyssa Sutherland"
  },
  {
   "id": 42174,
   "group": 2,
   "name": "Kay Lenz"
  },
  {
   "id": 110434,
   "group": 2,
   "name": "Anne Twomey"
  },
  {
   "id": 169805,
   "group": 2,
   "name": "Signy Coleman"
  },
  {
   "id": 54470,
   "group": 2,
   "name": "Lauren Ambrose"
  },
  {
   "id": 119227,
   "group": 2,
   "name": "Ellen McElduff"
  },
  {
   "id": 4493,
   "group": 2,
   "name": "Catherine Bell"
  },
  {
   "id": 58312,
   "group": 2,
   "name": "Angie Everhart"
  },
  {
   "id": 67838,
   "group": 2,
   "name": "Marianne Hagan"
  },
  {
   "id": 1214165,
   "group": 2,
   "name": "Michole Briana White"
  },
  {
   "id": 158769,
   "group": 2,
   "name": "Khrystyne Haje"
  },
  {
   "id": 28950,
   "group": 2,
   "name": "Lisa Eichhorn"
  },
  {
   "id": 21143,
   "group": 2,
   "name": "Allison Mackie"
  },
  {
   "id": 1217637,
   "group": 2,
   "name": "Denise Burse"
  },
  {
   "id": 112474,
   "group": 2,
   "name": "Elizabeth Keifer"
  },
  {
   "id": 143549,
   "group": 2,
   "name": "Rebekah Kennedy"
  },
  {
   "id": 73454,
   "group": 2,
   "name": "Kristen Hager"
  },
  {
   "id": 199264,
   "group": 2,
   "name": "Mary Beth Evans"
  },
  {
   "id": 1232604,
   "group": 2,
   "name": "Felecia M. Bell"
  },
  {
   "id": 53442,
   "group": 2,
   "name": "Yasmine Al Massri"
  },
  {
   "id": 162683,
   "group": 2,
   "name": "Katy Selverstone"
  },
  {
   "id": 36551,
   "group": 2,
   "name": "Daniela Sea"
  },
  {
   "id": 1214821,
   "group": 2,
   "name": "Nicole Leach"
  },
  {
   "id": 1544394,
   "group": 2,
   "name": "Aja Frary"
  },
  {
   "id": 89664,
   "group": 2,
   "name": "Fiona Hutchison"
  },
  {
   "id": 145058,
   "group": 2,
   "name": "Mariann Mayberry"
  },
  {
   "id": 4161,
   "group": 2,
   "name": "Patricia Charbonneau"
  },
  {
   "id": 70377,
   "group": 2,
   "name": "Beth Ehlers"
  }
 ],
 "links": [
  {
   "source": 122888,
   "target": 49425
  },
  {
   "source": 122888,
   "target": 143235
  },
  {
   "source": 73836,
   "target": 52776
  },
  {
   "source": 60632,
   "target": 21702
  },
  {
   "source": 10739,
   "target": 1232582
  },
  {
   "source": 1063,
   "target": 109869
  },
  {
   "source": 1063,
   "target": 65002
  },
  {
   "source": 109869,
   "target": 65002
  },
  {
   "source": 27855,
   "target": 4441
  },
  {
   "source": 20387,
   "target": 14702
  },
  {
   "source": 81953,
   "target": 40060
  },
  {
   "source": 49,
   "target": 11825
  },
  {
   "source": 49,
   "target": 70767
  },
  {
   "source": 49,
   "target": 13241
  },
  {
   "source": 49,
   "target": 935
  },
  {
   "source": 49,
   "target": 88598
  },
  {
   "source": 935,
   "target": 88598
  },
  {
   "source": 49,
   "target": 14892
  },
  {
   "source": 49,
   "target": 23627
  },
  {
   "source": 14892,
   "target": 23627
  },
  {
   "source": 49,
   "target": 31171
  },
  {
   "source": 49,
   "target": 65797
  },
  {
   "source": 49,
   "target": 19492
  },
  {
   "source": 49,
   "target": 43366
  },
  {
   "source": 49,
   "target": 74537
  },
  {
   "source": 155698,
   "target": 151363
  },
  {
   "source": 155698,
   "target": 78501
  },
  {
   "source": 155698,
   "target": 7796
  },
  {
   "source": 163906,
   "target": 34612
  },
  {
   "source": 172099,
   "target": 107033
  },
  {
   "source": 172099,
   "target": 13636
  },
  {
   "source": 107033,
   "target": 13636
  },
  {
   "source": 172099,
   "target": 70776
  },
  {
   "source": 172099,
   "target": 80988
  },
  {
   "source": 70776,
   "target": 80988
  },
  {
   "source": 163928,
   "target": 17640
  },
  {
   "source": 163928,
   "target": 59156
  },
  {
   "source": 99,
   "target": 91461
  },
  {
   "source": 99,
   "target": 56689
  },
  {
   "source": 99,
   "target": 4513
  },
  {
   "source": 99,
   "target": 82663
  },
  {
   "source": 99,
   "target": 64908
  },
  {
   "source": 99,
   "target": 88598
  },
  {
   "source": 99,
   "target": 85143
  },
  {
   "source": 65639,
   "target": 25869
  },
  {
   "source": 65639,
   "target": 78501
  },
  {
   "source": 73836,
   "target": 65797
  },
  {
   "source": 73836,
   "target": 1030995
  },
  {
   "source": 1216169,
   "target": 79792
  },
  {
   "source": 164040,
   "target": 198927
  },
  {
   "source": 164040,
   "target": 84247
  },
  {
   "source": 16845,
   "target": 42335
  },
  {
   "source": 16845,
   "target": 1215072
  },
  {
   "source": 42335,
   "target": 1215072
  },
  {
   "source": 10399,
   "target": 84457
  },
  {
   "source": 83701,
   "target": 161847
  },
  {
   "source": 65760,
   "target": 19265
  },
  {
   "source": 65760,
   "target": 39977
  },
  {
   "source": 19265,
   "target": 39977
  },
  {
   "source": 65760,
   "target": 4888
  },
  {
   "source": 65760,
   "target": 82663
  },
  {
   "source": 65760,
   "target": 4726
  },
  {
   "source": 65760,
   "target": 15250
  },
  {
   "source": 65760,
   "target": 27563
  },
  {
   "source": 65760,
   "target": 164397
  },
  {
   "source": 65760,
   "target": 1242775
  },
  {
   "source": 99351,
   "target": 14415
  },
  {
   "source": 52929,
   "target": 78501
  },
  {
   "source": 5958,
   "target": 14702
  },
  {
   "source": 65797,
   "target": 177443
  },
  {
   "source": 65797,
   "target": 17640
  },
  {
   "source": 65797,
   "target": 20047
  },
  {
   "source": 49425,
   "target": 86468
  },
  {
   "source": 49425,
   "target": 4726
  },
  {
   "source": 49425,
   "target": 21044
  },
  {
   "source": 58692,
   "target": 31649
  },
  {
   "source": 58692,
   "target": 65345
  },
  {
   "source": 31649,
   "target": 65345
  },
  {
   "source": 164149,
   "target": 1218184
  },
  {
   "source": 164149,
   "target": 6751
  },
  {
   "source": 1218184,
   "target": 6751
  },
  {
   "source": 74687,
   "target": 59261
  },
  {
   "source": 17495,
   "target": 39388
  },
  {
   "source": 1106256,
   "target": 11617
  },
  {
   "source": 18285,
   "target": 78501
  },
  {
   "source": 59206,
   "target": 59257
  },
  {
   "source": 16845,
   "target": 145814
  },
  {
   "source": 16845,
   "target": 26009
  },
  {
   "source": 16845,
   "target": 65002
  },
  {
   "source": 16845,
   "target": 20387
  },
  {
   "source": 16845,
   "target": 7796
  },
  {
   "source": 16845,
   "target": 92327
  },
  {
   "source": 21711,
   "target": 5958
  },
  {
   "source": 16859,
   "target": 52929
  },
  {
   "source": 16859,
   "target": 1074628
  },
  {
   "source": 16859,
   "target": 34200
  },
  {
   "source": 109740,
   "target": 14984
  },
  {
   "source": 8691,
   "target": 70776
  },
  {
   "source": 8691,
   "target": 30485
  },
  {
   "source": 8691,
   "target": 1308445
  },
  {
   "source": 1221134,
   "target": 38024
  },
  {
   "source": 27855,
   "target": 139150
  },
  {
   "source": 107033,
   "target": 20387
  },
  {
   "source": 17495,
   "target": 64908
  },
  {
   "source": 115240,
   "target": 51544
  },
  {
   "source": 115240,
   "target": 163115
  },
  {
   "source": 115240,
   "target": 141610
  },
  {
   "source": 115240,
   "target": 21216
  },
  {
   "source": 164397,
   "target": 92728
  },
  {
   "source": 164397,
   "target": 121566
  },
  {
   "source": 164397,
   "target": 91461
  },
  {
   "source": 164397,
   "target": 167604
  },
  {
   "source": 26009,
   "target": 204468
  },
  {
   "source": 42694,
   "target": 118546
  },
  {
   "source": 41555,
   "target": 21369
  },
  {
   "source": 41555,
   "target": 78501
  },
  {
   "source": 41555,
   "target": 540281
  },
  {
   "source": 78501,
   "target": 540281
  },
  {
   "source": 91461,
   "target": 20767
  },
  {
   "source": 126713,
   "target": 54470
  },
  {
   "source": 28412,
   "target": 20387
  },
  {
   "source": 1030995,
   "target": 23959
  },
  {
   "source": 17187,
   "target": 2525
  },
  {
   "source": 4888,
   "target": 64908
  },
  {
   "source": 26009,
   "target": 78434
  },
  {
   "source": 49824,
   "target": 73569
  },
  {
   "source": 49824,
   "target": 1345418
  },
  {
   "source": 49824,
   "target": 208659
  },
  {
   "source": 49824,
   "target": 17640
  },
  {
   "source": 58692,
   "target": 1308445
  },
  {
   "source": 156342,
   "target": 133451
  },
  {
   "source": 33488,
   "target": 134178
  },
  {
   "source": 33488,
   "target": 1063
  },
  {
   "source": 33488,
   "target": 14668
  },
  {
   "source": 119227,
   "target": 39730
  },
  {
   "source": 141610,
   "target": 14702
  },
  {
   "source": 42694,
   "target": 177022
  },
  {
   "source": 1090276,
   "target": 109869
  },
  {
   "source": 1090276,
   "target": 50346
  },
  {
   "source": 1090276,
   "target": 58312
  },
  {
   "source": 82663,
   "target": 1213613
  },
  {
   "source": 82663,
   "target": 11024
  },
  {
   "source": 1213613,
   "target": 11024
  },
  {
   "source": 82663,
   "target": 4888
  },
  {
   "source": 82663,
   "target": 109869
  },
  {
   "source": 39388,
   "target": 40060
  },
  {
   "source": 37252,
   "target": 212154
  },
  {
   "source": 15250,
   "target": 27855
  },
  {
   "source": 27855,
   "target": 7796
  },
  {
   "source": 42174,
   "target": 26009
  },
  {
   "source": 64826,
   "target": 65002
  },
  {
   "source": 8985,
   "target": 1157294
  },
  {
   "source": 8985,
   "target": 20767
  },
  {
   "source": 1157294,
   "target": 20767
  },
  {
   "source": 8985,
   "target": 109740
  },
  {
   "source": 8985,
   "target": 64908
  },
  {
   "source": 17187,
   "target": 14984
  },
  {
   "source": 74537,
   "target": 21702
  },
  {
   "source": 74537,
   "target": 19265
  },
  {
   "source": 74537,
   "target": 52776
  },
  {
   "source": 19265,
   "target": 52776
  },
  {
   "source": 118043,
   "target": 161847
  },
  {
   "source": 58168,
   "target": 170880
  },
  {
   "source": 58168,
   "target": 4441
  },
  {
   "source": 19492,
   "target": 79997
  },
  {
   "source": 74612,
   "target": 30485
  },
  {
   "source": 74612,
   "target": 4513
  },
  {
   "source": 33655,
   "target": 77803
  },
  {
   "source": 33655,
   "target": 1214165
  },
  {
   "source": 33655,
   "target": 4721
  },
  {
   "source": 33655,
   "target": 95039
  },
  {
   "source": 4721,
   "target": 95039
  },
  {
   "source": 1213305,
   "target": 5958
  },
  {
   "source": 1213305,
   "target": 121566
  },
  {
   "source": 935,
   "target": 21216
  },
  {
   "source": 935,
   "target": 28950
  },
  {
   "source": 74932,
   "target": 58966
  },
  {
   "source": 18285,
   "target": 28024
  },
  {
   "source": 74687,
   "target": 47882
  },
  {
   "source": 82885,
   "target": 167604
  },
  {
   "source": 82885,
   "target": 21711
  },
  {
   "source": 58312,
   "target": 1034453
  },
  {
   "source": 58312,
   "target": 177443
  },
  {
   "source": 58312,
   "target": 14702
  },
  {
   "source": 62127,
   "target": 5578
  },
  {
   "source": 58369,
   "target": 11671
  },
  {
   "source": 28412,
   "target": 212154
  },
  {
   "source": 1157294,
   "target": 1170657
  },
  {
   "source": 99351,
   "target": 19492
  },
  {
   "source": 99351,
   "target": 14892
  },
  {
   "source": 19492,
   "target": 14892
  },
  {
   "source": 99351,
   "target": 5578
  },
  {
   "source": 99351,
   "target": 4726
  },
  {
   "source": 99351,
   "target": 15423
  },
  {
   "source": 1063,
   "target": 134082
  },
  {
   "source": 1063,
   "target": 9281
  },
  {
   "source": 1063,
   "target": 134178
  },
  {
   "source": 1063,
   "target": 14984
  },
  {
   "source": 1063,
   "target": 77803
  },
  {
   "source": 1063,
   "target": 23627
  },
  {
   "source": 1063,
   "target": 42335
  },
  {
   "source": 1063,
   "target": 59156
  },
  {
   "source": 1063,
   "target": 21369
  },
  {
   "source": 59156,
   "target": 21369
  },
  {
   "source": 5578,
   "target": 121566
  },
  {
   "source": 9281,
   "target": 59206
  },
  {
   "source": 9281,
   "target": 100867
  },
  {
   "source": 9281,
   "target": 112474
  },
  {
   "source": 4687,
   "target": 15007
  },
  {
   "source": 1102,
   "target": 64908
  },
  {
   "source": 43366,
   "target": 14892
  },
  {
   "source": 17495,
   "target": 25836
  },
  {
   "source": 17495,
   "target": 3664
  },
  {
   "source": 17495,
   "target": 4687
  },
  {
   "source": 17495,
   "target": 5578
  },
  {
   "source": 3664,
   "target": 4687
  },
  {
   "source": 3664,
   "target": 5578
  },
  {
   "source": 4687,
   "target": 5578
  },
  {
   "source": 17495,
   "target": 20387
  },
  {
   "source": 17495,
   "target": 187565
  },
  {
   "source": 143549,
   "target": 31649
  },
  {
   "source": 50346,
   "target": 11671
  },
  {
   "source": 50346,
   "target": 15441
  },
  {
   "source": 50346,
   "target": 70852
  },
  {
   "source": 50346,
   "target": 59261
  },
  {
   "source": 50346,
   "target": 31167
  },
  {
   "source": 59261,
   "target": 31167
  },
  {
   "source": 1213613,
   "target": 18285
  },
  {
   "source": 1213613,
   "target": 21044
  },
  {
   "source": 31649,
   "target": 171901
  },
  {
   "source": 1214165,
   "target": 19492
  },
  {
   "source": 39388,
   "target": 64908
  },
  {
   "source": 38024,
   "target": 155574
  },
  {
   "source": 17640,
   "target": 20387
  },
  {
   "source": 17640,
   "target": 133451
  },
  {
   "source": 25836,
   "target": 11825
  },
  {
   "source": 25836,
   "target": 59261
  },
  {
   "source": 25836,
   "target": 3664
  },
  {
   "source": 25836,
   "target": 22127
  },
  {
   "source": 3664,
   "target": 22127
  },
  {
   "source": 25869,
   "target": 73454
  },
  {
   "source": 25869,
   "target": 168610
  },
  {
   "source": 25869,
   "target": 21702
  },
  {
   "source": 168610,
   "target": 21702
  },
  {
   "source": 25869,
   "target": 84247
  },
  {
   "source": 25869,
   "target": 11024
  },
  {
   "source": 84247,
   "target": 11024
  },
  {
   "source": 25869,
   "target": 21369
  },
  {
   "source": 58643,
   "target": 11705
  },
  {
   "source": 58643,
   "target": 126713
  },
  {
   "source": 58643,
   "target": 14892
  },
  {
   "source": 58643,
   "target": 6751
  },
  {
   "source": 14892,
   "target": 6751
  },
  {
   "source": 100395,
   "target": 14668
  },
  {
   "source": 51544,
   "target": 70852
  },
  {
   "source": 91461,
   "target": 20189
  },
  {
   "source": 91461,
   "target": 14668
  },
  {
   "source": 58692,
   "target": 39977
  },
  {
   "source": 42335,
   "target": 31167
  },
  {
   "source": 42335,
   "target": 20387
  },
  {
   "source": 42335,
   "target": 21216
  },
  {
   "source": 9782,
   "target": 51544
  },
  {
   "source": 84247,
   "target": 6681
  },
  {
   "source": 34200,
   "target": 64908
  },
  {
   "source": 34200,
   "target": 120831
  },
  {
   "source": 34200,
   "target": 39388
  },
  {
   "source": 120831,
   "target": 39388
  },
  {
   "source": 26009,
   "target": 121566
  },
  {
   "source": 26009,
   "target": 134082
  },
  {
   "source": 26009,
   "target": 11024
  },
  {
   "source": 26009,
   "target": 58966
  },
  {
   "source": 4687,
   "target": 14415
  },
  {
   "source": 62547,
   "target": 121566
  },
  {
   "source": 1222175,
   "target": 4726
  },
  {
   "source": 1222175,
   "target": 4687
  },
  {
   "source": 9782,
   "target": 19265
  },
  {
   "source": 9782,
   "target": 21711
  },
  {
   "source": 59696,
   "target": 130513
  },
  {
   "source": 52929,
   "target": 21702
  },
  {
   "source": 52929,
   "target": 20767
  },
  {
   "source": 133047,
   "target": 54124
  },
  {
   "source": 42694,
   "target": 141610
  },
  {
   "source": 77803,
   "target": 78501
  },
  {
   "source": 83701,
   "target": 84247
  },
  {
   "source": 59156,
   "target": 11705
  },
  {
   "source": 34612,
   "target": 4687
  },
  {
   "source": 34612,
   "target": 6681
  },
  {
   "source": 34612,
   "target": 59206
  },
  {
   "source": 1226076,
   "target": 39977
  },
  {
   "source": 11825,
   "target": 4513
  },
  {
   "source": 20387,
   "target": 81321
  },
  {
   "source": 18261,
   "target": 139150
  },
  {
   "source": 18261,
   "target": 15423
  },
  {
   "source": 18261,
   "target": 126713
  },
  {
   "source": 109869,
   "target": 13636
  },
  {
   "source": 4441,
   "target": 54124
  },
  {
   "source": 18282,
   "target": 126713
  },
  {
   "source": 18285,
   "target": 73569
  },
  {
   "source": 18285,
   "target": 1157294
  },
  {
   "source": 18285,
   "target": 14702
  },
  {
   "source": 5578,
   "target": 64908
  },
  {
   "source": 100867,
   "target": 122231
  },
  {
   "source": 1218223,
   "target": 14892
  },
  {
   "source": 59257,
   "target": 10739
  },
  {
   "source": 59257,
   "target": 44830
  },
  {
   "source": 10739,
   "target": 44830
  },
  {
   "source": 1443708,
   "target": 141610
  },
  {
   "source": 59261,
   "target": 204468
  },
  {
   "source": 59261,
   "target": 14984
  },
  {
   "source": 59261,
   "target": 31140
  },
  {
   "source": 1345418,
   "target": 1308445
  },
  {
   "source": 1345418,
   "target": 2453
  },
  {
   "source": 1345418,
   "target": 161847
  },
  {
   "source": 133047,
   "target": 39388
  },
  {
   "source": 11671,
   "target": 163695
  },
  {
   "source": 19492,
   "target": 11825
  },
  {
   "source": 118043,
   "target": 52996
  },
  {
   "source": 11825,
   "target": 79792
  },
  {
   "source": 1544394,
   "target": 37252
  },
  {
   "source": 10739,
   "target": 65002
  },
  {
   "source": 10739,
   "target": 167604
  },
  {
   "source": 10399,
   "target": 23627
  },
  {
   "source": 10399,
   "target": 1226076
  },
  {
   "source": 149665,
   "target": 159325
  },
  {
   "source": 149665,
   "target": 154769
  },
  {
   "source": 159325,
   "target": 154769
  },
  {
   "source": 149665,
   "target": 20767
  },
  {
   "source": 149665,
   "target": 20189
  },
  {
   "source": 92327,
   "target": 5958
  },
  {
   "source": 1157294,
   "target": 73569
  },
  {
   "source": 1034453,
   "target": 110742
  },
  {
   "source": 1034453,
   "target": 540281
  },
  {
   "source": 110742,
   "target": 540281
  },
  {
   "source": 1034453,
   "target": 4721
  },
  {
   "source": 13636,
   "target": 23959
  },
  {
   "source": 67838,
   "target": 21321
  },
  {
   "source": 84247,
   "target": 11617
  },
  {
   "source": 84247,
   "target": 21702
  },
  {
   "source": 84247,
   "target": 15250
  },
  {
   "source": 133401,
   "target": 143549
  },
  {
   "source": 133401,
   "target": 6681
  },
  {
   "source": 59687,
   "target": 177022
  },
  {
   "source": 133451,
   "target": 54124
  },
  {
   "source": 133451,
   "target": 171673
  },
  {
   "source": 54124,
   "target": 171673
  },
  {
   "source": 51544,
   "target": 15109
  },
  {
   "source": 43366,
   "target": 56689
  },
  {
   "source": 2453,
   "target": 15007
  },
  {
   "source": 2453,
   "target": 14415
  },
  {
   "source": 2453,
   "target": 64908
  },
  {
   "source": 2453,
   "target": 21044
  },
  {
   "source": 2453,
   "target": 4726
  },
  {
   "source": 2453,
   "target": 14702
  },
  {
   "source": 2453,
   "target": 109869
  },
  {
   "source": 2453,
   "target": 93663
  },
  {
   "source": 84422,
   "target": 38024
  },
  {
   "source": 5958,
   "target": 63735
  },
  {
   "source": 118546,
   "target": 54470
  },
  {
   "source": 109024,
   "target": 52776
  },
  {
   "source": 84462,
   "target": 14984
  },
  {
   "source": 84462,
   "target": 70776
  },
  {
   "source": 84462,
   "target": 134365
  },
  {
   "source": 84462,
   "target": 11024
  },
  {
   "source": 10739,
   "target": 27855
  },
  {
   "source": 134082,
   "target": 999346
  },
  {
   "source": 100867,
   "target": 77803
  },
  {
   "source": 100867,
   "target": 52776
  },
  {
   "source": 4721,
   "target": 6681
  },
  {
   "source": 92728,
   "target": 4441
  },
  {
   "source": 92728,
   "target": 59962
  },
  {
   "source": 92728,
   "target": 3664
  },
  {
   "source": 92728,
   "target": 24305
  },
  {
   "source": 59962,
   "target": 12932
  },
  {
   "source": 59962,
   "target": 81321
  },
  {
   "source": 1215072,
   "target": 52002
  },
  {
   "source": 13636,
   "target": 31171
  },
  {
   "source": 27260,
   "target": 64908
  },
  {
   "source": 27260,
   "target": 65002
  },
  {
   "source": 60034,
   "target": 1308445
  },
  {
   "source": 60034,
   "target": 24305
  },
  {
   "source": 60034,
   "target": 13636
  },
  {
   "source": 60034,
   "target": 31171
  },
  {
   "source": 101028,
   "target": 110463
  },
  {
   "source": 101028,
   "target": 85143
  },
  {
   "source": 1100549,
   "target": 109869
  },
  {
   "source": 11024,
   "target": 21143
  },
  {
   "source": 110463,
   "target": 4687
  },
  {
   "source": 126713,
   "target": 120831
  },
  {
   "source": 53260,
   "target": 20767
  },
  {
   "source": 19265,
   "target": 6751
  },
  {
   "source": 19265,
   "target": 110742
  },
  {
   "source": 84877,
   "target": 6681
  },
  {
   "source": 110463,
   "target": 21369
  },
  {
   "source": 27563,
   "target": 20387
  },
  {
   "source": 27563,
   "target": 110434
  },
  {
   "source": 134082,
   "target": 60632
  },
  {
   "source": 134082,
   "target": 21124
  },
  {
   "source": 60632,
   "target": 21124
  },
  {
   "source": 134082,
   "target": 21216
  },
  {
   "source": 4888,
   "target": 204468
  },
  {
   "source": 134178,
   "target": 93663
  },
  {
   "source": 19492,
   "target": 109869
  },
  {
   "source": 19492,
   "target": 15109
  },
  {
   "source": 86468,
   "target": 62220
  },
  {
   "source": 85143,
   "target": 11825
  },
  {
   "source": 85143,
   "target": 5578
  },
  {
   "source": 85143,
   "target": 65002
  },
  {
   "source": 5578,
   "target": 65002
  },
  {
   "source": 109740,
   "target": 15423
  },
  {
   "source": 1223878,
   "target": 120831
  },
  {
   "source": 27855,
   "target": 11705
  },
  {
   "source": 3282,
   "target": 78788
  },
  {
   "source": 109869,
   "target": 54124
  },
  {
   "source": 109869,
   "target": 6751
  },
  {
   "source": 54124,
   "target": 6751
  },
  {
   "source": 11617,
   "target": 11671
  },
  {
   "source": 11617,
   "target": 5958
  },
  {
   "source": 11617,
   "target": 52929
  },
  {
   "source": 11617,
   "target": 28412
  },
  {
   "source": 21143,
   "target": 171649
  },
  {
   "source": 11705,
   "target": 70852
  },
  {
   "source": 93663,
   "target": 20387
  },
  {
   "source": 118247,
   "target": 21711
  },
  {
   "source": 52776,
   "target": 14984
  },
  {
   "source": 4687,
   "target": 171075
  },
  {
   "source": 20047,
   "target": 167604
  },
  {
   "source": 1232500,
   "target": 70767
  },
  {
   "source": 21216,
   "target": 121566
  },
  {
   "source": 1216169,
   "target": 110463
  },
  {
   "source": 20189,
   "target": 21044
  },
  {
   "source": 20189,
   "target": 20387
  },
  {
   "source": 167604,
   "target": 7796
  },
  {
   "source": 167604,
   "target": 65421
  },
  {
   "source": 167604,
   "target": 39730
  },
  {
   "source": 36551,
   "target": 20387
  },
  {
   "source": 20189,
   "target": 21129
  },
  {
   "source": 20189,
   "target": 14415
  },
  {
   "source": 20189,
   "target": 1308445
  },
  {
   "source": 28412,
   "target": 21369
  },
  {
   "source": 52996,
   "target": 21044
  },
  {
   "source": 118546,
   "target": 31167
  },
  {
   "source": 118546,
   "target": 38024
  },
  {
   "source": 151363,
   "target": 80622
  },
  {
   "source": 4441,
   "target": 122231
  },
  {
   "source": 53260,
   "target": 15423
  },
  {
   "source": 20767,
   "target": 15007
  },
  {
   "source": 4441,
   "target": 22127
  },
  {
   "source": 37252,
   "target": 121566
  },
  {
   "source": 4513,
   "target": 21044
  },
  {
   "source": 86468,
   "target": 65345
  },
  {
   "source": 4687,
   "target": 6751
  },
  {
   "source": 4687,
   "target": 6681
  },
  {
   "source": 4687,
   "target": 38024
  },
  {
   "source": 70377,
   "target": 169805
  },
  {
   "source": 4721,
   "target": 30485
  },
  {
   "source": 4726,
   "target": 70852
  },
  {
   "source": 21124,
   "target": 56825
  },
  {
   "source": 21124,
   "target": 65002
  },
  {
   "source": 21129,
   "target": 6751
  },
  {
   "source": 21129,
   "target": 54124
  },
  {
   "source": 168610,
   "target": 171075
  },
  {
   "source": 78501,
   "target": 47882
  },
  {
   "source": 176823,
   "target": 14668
  },
  {
   "source": 177022,
   "target": 171075
  },
  {
   "source": 13636,
   "target": 40060
  },
  {
   "source": 70767,
   "target": 65421
  },
  {
   "source": 38024,
   "target": 73569
  },
  {
   "source": 21702,
   "target": 14668
  },
  {
   "source": 177443,
   "target": 1218005
  },
  {
   "source": 13636,
   "target": 30485
  },
  {
   "source": 5578,
   "target": 171649
  },
  {
   "source": 5578,
   "target": 23959
  },
  {
   "source": 5578,
   "target": 15007
  },
  {
   "source": 14668,
   "target": 145814
  },
  {
   "source": 31167,
   "target": 88598
  },
  {
   "source": 39388,
   "target": 65421
  },
  {
   "source": 121566,
   "target": 24305
  },
  {
   "source": 15423,
   "target": 65421
  },
  {
   "source": 1039525,
   "target": 1170657
  }
 ]
}