[
 {
  "year": -10,
  "freq": 27.0,
  "rating": 69.66666666666667
 },
 {
  "year": -9,
  "freq": 37.2,
  "rating": 64.4
 },
 {
  "year": -8,
  "freq": 39.0,
  "rating": 66.6
 },
 {
  "year": -7,
  "freq": 36.0,
  "rating": 59.166666666666664
 },
 {
  "year": -6,
  "freq": 51.5,
  "rating": 65.0
 },
 {
  "year": -5,
  "freq": 55.333333333333336,
  "rating": 59.0
 },
 {
  "year": -4,
  "freq": 51.9,
  "rating": 69.0
 },
 {
  "year": -3,
  "freq": 33.714285714285715,
  "rating": 64.57142857142857
 },
 {
  "year": -2,
  "freq": 47.54545454545455,
  "rating": 57.0
 },
 {
  "year": -1,
  "freq": 49.2,
  "rating": 59.9
 },
 {
  "year": 1,
  "freq": 58.666666666666664,
  "rating": 62.733333333333334
 },
 {
  "year": 2,
  "freq": 43.857142857142854,
  "rating": 62.714285714285715
 },
 {
  "year": 3,
  "freq": 81.83333333333333,
  "rating": 67.0
 },
 {
  "year": 4,
  "freq": 62.0,
  "rating": 60.69230769230769
 },
 {
  "year": 5,
  "freq": 59.714285714285715,
  "rating": 65.14285714285714
 },
 {
  "year": 6,
  "freq": 0,
  "rating": 0
 },
 {
  "year": 7,
  "freq": 0,
  "rating": 0
 },
 {
  "year": 8,
  "freq": 0,
  "rating": 0
 },
 {
  "year": 9,
  "freq": 0,
  "rating": 0
 },
 {
  "year": 10,
  "freq": 0,
  "rating": 0
 }
]